{
  "$schema": "https://schema.management.azure.com/schemas/2015-01-01/deploymentTemplate.json#",
  "contentVersion": "1.0.0.0",
  "parameters": {
    "commonSettings": {
      "type": "object",
      "metadata": {
        "Description": "common settings object"
      }
    },
    "networkSettings": {
      "type": "object",
      "metadata": {
        "Description": "Network settings object"
      }
    },
    "masterSettings": {
      "type": "object",
      "metadata": {
        "Description": "master settings object"
      }
    },
    "masterOSSettings": {
      "type": "object",
      "metadata": {
        "Description": "master OS settings object"
      }
    }
  },
  "variables": {
    "location": "[resourceGroup().location]",
    "vmScripts": {
      "scriptsToDownload": [
        "[concat(variables('scriptUrl'), 'master-setup.ps1')]"
      ],
      "commandToExecute": ""
    },
    "scriptUrl": "https://raw.githubusercontent.com/xpillons/azure-hpc/master/Compute-Grid-Infra/",
    "sharedAccountId": "[resourceId(parameters('commonSettings').RGStorageName, 'Microsoft.Storage/storageAccounts', parameters('commonSettings').DataSAName)]",
    "computeApiVersion": "2016-03-30",
    "storageApiVersion": "2015-06-15"
  },
  "resources": [
    {
      "type": "Microsoft.Compute/virtualMachines",
      "name": "[parameters('masterSettings').Name]",
      "location": "[variables('location')]",
      "apiVersion": "[variables('computeApiVersion')]",
      "dependsOn": [
      ],
      "properties": {
        "hardwareProfile": {
          "vmSize": "[parameters('masterSettings').VMsku]"
        },
        "osProfile": {
          "computerName": "[parameters('masterSettings').Name]",
          "adminUsername": "[parameters('masterOSSettings').adminUserName]",
          "adminPassword": "[parameters('masterOSSettings').adminPassword]"
        },
        "storageProfile": {
          "imageReference": "[parameters('masterOSSettings').imageReference]",
          "osDisk": {
            "name": "[parameters('masterSettings').OSDiskName]",
            "vhd": {
              "uri": "[concat('http://',parameters('masterSettings').SAName,'.blob.core.windows.net/',parameters('masterSettings').VHDContainerName,'/',parameters('masterSettings').OSDiskName,'.vhd')]"
            },
            "caching": "ReadOnly",
            "createOption": "FromImage"
          }
        },
        "networkProfile": {
          "networkInterfaces": [
            {
              "id": "[resourceId('Microsoft.Network/networkInterfaces',parameters('masterSettings').NicName)]"
            }
          ]
        },
        "diagnosticsProfile": {
          "bootDiagnostics": {
            "enabled": "true",
            "storageUri": "[concat('http://',parameters('masterSettings').DiagSAName,'.blob.core.windows.net')]"
          }
        }
      },
        "resources": [
          {
            "name": "WindowsMasterExtension",
            "type": "extensions",
            "location": "[variables('location')]",
            "apiVersion": "[variables('storageApiVersion')]",
            "dependsOn": [
              "[concat('Microsoft.Compute/virtualMachines/', parameters('masterSettings').Name)]"
            ],
            "tags": {
              "displayName": "WindowsMasterExtension"
            },
            "properties": {
              "publisher": "Microsoft.Compute",
              "type": "CustomScriptExtension",
              "typeHandlerVersion": "1.4",
              "autoUpgradeMinorVersion": true,
              "settings": {
                "fileUris": [
                ],
                "commandToExecute": "hostname"
              }
            }
          }
        ]
    }
  ]
}